src/__init__.py
src/__main__.py
src/server.py
takanarishimbo_ros2_exec_mcp-0.2.2.dist-info/METADATA
takanarishimbo_ros2_exec_mcp-0.2.2.dist-info/WHEEL
takanarishimbo_ros2_exec_mcp-0.2.2.dist-info/entry_points.txt
takanarishimbo_ros2_exec_mcp-0.2.2.dist-info/RECORD
