Metadata-Version: 2.4
Name: takanarishimbo-ros2-exec-mcp
Version: 0.2.2
Summary: An MCP server that executes ROS 2 (ros2) CLI commands
Project-URL: Homepage, https://github.com/TakanariShimbo/ros2-exec-mcp
Project-URL: Repository, https://github.com/TakanariShimbo/ros2-exec-mcp.git
Project-URL: Issues, https://github.com/TakanariShimbo/ros2-exec-mcp/issues
Author-email: Takanari Shimbo <takanari.shimbo@gmail.com>
License: MIT
Keywords: cli,executor,mcp,ros2,server
Classifier: Development Status :: 4 - Beta
Classifier: Intended Audience :: Developers
Classifier: License :: OSI Approved :: MIT License
Classifier: Programming Language :: Python :: 3
Classifier: Programming Language :: Python :: 3.10
Classifier: Programming Language :: Python :: 3.11
Classifier: Programming Language :: Python :: 3.12
Classifier: Topic :: Software Development :: Libraries
Requires-Python: >=3.10
Requires-Dist: mcp>=1.1.0
